decision_tree/__init__.py
decision_tree/decision_tree_clf.py
decision_tree/decision_tree_reg.py
decision_tree_dmazilkin-0.1.1.dist-info/METADATA
decision_tree_dmazilkin-0.1.1.dist-info/WHEEL
decision_tree_dmazilkin-0.1.1.dist-info/RECORD
