Metadata-Version: 2.3
Name: decision-tree-dmazilkin
Version: 0.1.1
Summary: This package contains the Decition Tree algrotihm implementation.
License: MIT
Author: Dmitrii Mazilkin
Author-email: dim.mazilkin@gmail.com
Requires-Python: >=3.12
Classifier: License :: OSI Approved :: MIT License
Classifier: Programming Language :: Python :: 3
Classifier: Programming Language :: Python :: 3.12
Classifier: Programming Language :: Python :: 3.13
Requires-Dist: matplotlib (>=3.10.5,<4.0.0)
Requires-Dist: numpy (>=2.3.2,<3.0.0)
Requires-Dist: pandas (>=2.3.1,<3.0.0)
Requires-Dist: scikit-learn (>=1.7.1,<2.0.0)
